{"children":{"visits":{"children":{"treatment":{"children":{"rtx_details":{"children":{"SBRT_YN":{"displayName":"是否立体定向放疗","type":"string"},"RTX_SITE":{"displayName":"放疗部位","type":"string"}},"displayName":"放疗详情"},"lvop_details":{"children":{"LVOP_DATE":{"displayName":"手术日期","format":"yyyy-mm-dd","type":"date"},"LVOP_TYPE":{"displayName":"手术类型","type":"string"}},"displayName":"肝脏手术治疗详情"},"LIVR_NTVXN_YN":{"displayName":"有无肝脏介入治疗","type":"string"},"RTX_YN":{"displayName":"有无放疗","type":"string"},"LIVER_OPRT_YN":{"displayName":"有无肝脏手术治疗","type":"string"},"lvnv_details":{"children":{"LVNV_TYPE":{"displayName":"介入治疗类型","type":"string"},"LVNV_DATE":{"displayName":"介入治疗日期","format":"yyyy-mm-dd","type":"date"}},"displayName":"肝脏介入治疗详情"},"cmtgt_details":{"children":{"CMTGT_START_DATE":{"displayName":"治疗开始日期","format":"yyyy-mm-dd","type":"date"},"CMTGT_DRUG_NAME":{"displayName":"药物名称","type":"string"},"CMTGT_END_DATE":{"displayName":"治疗结束日期","format":"yyyy-mm-dd","type":"date"},"CMTGT_PROTOCOL_NAME":{"displayName":"方案名称","type":"string"}},"displayName":"化疗及靶向治疗详情"},"CHEMO_TRGT_YN":{"displayName":"有无化疗及靶向治疗","type":"string"}},"displayName":"治疗"},"test":{"children":{"HBV_I_YN":{"displayName":"有无HBV免疫学检验","type":"string"},"CF_YN":{"displayName":"有无凝血功能检验","type":"string"},"blood_routine":{"children":{"PLT_REF":{"displayName":"血小板计数参考值范围","type":"string"},"HB_REF":{"displayName":"血红蛋白参考值范围","type":"string"},"BR_TEST_DATE":{"displayName":"报告日期","format":"yyyy-mm-dd","type":"date"},"HB_VALUE":{"displayName":"血红蛋白（g/L）","type":"double"},"WBC_VALUE":{"displayName":"白细胞计数（10^9/L）","type":"double"},"NR_REF":{"displayName":"中性粒细胞百分比参考值范围","type":"string"},"RBC_VALUE":{"displayName":"红细胞计数（10^12/L）","type":"double"},"PLT_VALUE":{"displayName":"血小板计数（10^9/L）","type":"double"},"WBC_REF":{"displayName":"白细胞计数参考值范围","type":"string"},"RBC_REF":{"displayName":"红细胞计数参考值范围","type":"string"},"N_VALUE":{"displayName":"中性粒细胞计数（10^9/L）","type":"double"},"NV_REF":{"displayName":"中性粒细胞计数参考值范围","type":"string"},"N_RATIO":{"displayName":"中性粒细胞百分比（%）","type":"double"}},"displayName":"血常规"},"liver_and_kidney_function":{"children":{"ALT_VALUE":{"displayName":"谷丙转氨酶（U/L）","type":"double"},"UREA_VALUE":{"displayName":"尿素（mmol/L）","type":"double"},"LDH_REF":{"displayName":"乳酸脱氢酶参考值范围","type":"string"},"TP_VALUE":{"displayName":"总蛋白（g/L）","type":"double"},"ALB_VALUE":{"displayName":"白蛋白（g/L）","type":"double"},"CREATININE_VALUE":{"displayName":"肌酐（μmol/L）","type":"double"},"TBIL_VALUE":{"displayName":"总胆红素（μmol/L）","type":"double"},"CR_REF":{"displayName":"肌酐参考值范围","type":"string"},"BG_VALUE":{"displayName":"血糖（mmol/L）","type":"double"},"ALT_REF":{"displayName":"谷丙转氨酶参考值范围","type":"string"},"UREA_REF":{"displayName":"尿素参考值范围","type":"string"},"UA_REF":{"displayName":"尿酸参考值范围","type":"string"},"DBIL_REF":{"displayName":"直接胆红素参考值范围","type":"string"},"BG_REF":{"displayName":"血糖参考值范围","type":"string"},"TBIL_REF":{"displayName":"总胆红素参考值范围","type":"string"},"AST_VALUE":{"displayName":"谷草转氨酶（U/L）","type":"double"},"UA_VALUE":{"displayName":"尿酸（μmol/L）","type":"double"},"LKF_TEST_DATE":{"displayName":"报告日期","format":"yyyy-mm-dd","type":"date"},"AST_REF":{"displayName":"谷草转氨酶参考值范围","type":"string"},"ALB_REF":{"displayName":"白蛋白参考值范围","type":"string"},"LDH_VALUE":{"displayName":"乳酸脱氢酶（LDH）（U/L）","type":"double"},"TP_REF":{"displayName":"总蛋白参考值范围","type":"string"},"DBIL_VALUE":{"displayName":"直接胆红素（μmol/L）","type":"double"}},"displayName":"肝肾功能"},"hbv_immunology_qual":{"children":{"HBEAB_QUAL_VAL":{"displayName":"乙肝病毒e抗体结果","type":"string"},"HBVI_QUAL_TEST_DATE":{"displayName":"报告日期","format":"yyyy-mm-dd","type":"date"},"HBCAB_QUAL_VAL":{"displayName":"乙肝病毒核心抗体结果","type":"string"},"HBSAB_QUAL_VAL":{"displayName":"乙肝病毒表面抗体结果","type":"string"},"HBEAG_QUAL_VAL":{"displayName":"乙肝病毒e抗原结果","type":"string"},"HBSAG_QUAL_VAL":{"displayName":"乙肝病毒表面抗原结果","type":"string"}},"displayName":"HBV免疫学（定性）"},"hbv_immunology_quant":{"children":{"HBCAB_QUANT_UNIT":{"displayName":"乙肝病毒核心抗体单位","type":"string"},"HBEAB_QUANT_UNIT":{"displayName":"乙肝病毒e抗体单位","type":"string"},"HBCAB_QUANT_REF":{"displayName":"乙肝病毒核心抗体参考值范围","type":"string"},"HBSAB_QUANT_REF":{"displayName":"乙肝病毒表面抗体参考值范围","type":"string"},"HBEAG_QUANT_UNIT":{"displayName":"乙肝病毒e抗原单位","type":"string"},"HBEAB_QUANT_REF":{"displayName":"乙肝病毒e抗体参考值范围","type":"string"},"HBSAG_QUANT_UNIT":{"displayName":"乙肝病毒表面抗原单位","type":"string"},"HBSAG_QUANT_VAL":{"displayName":"乙肝病毒表面抗原结果","type":"double"},"HBEAG_QUANT_REF":{"displayName":"乙肝病毒e抗原参考值范围","type":"string"},"HBVI_QUANT_TEST_DATE":{"displayName":"报告日期","format":"yyyy-mm-dd","type":"date"},"HBEAG_QUANT_VAL":{"displayName":"乙肝病毒e抗原结果","type":"double"},"HBSAB_QUANT_UNIT":{"displayName":"乙肝病毒表面抗体单位","type":"string"},"HBCAB_QUANT_VAL":{"displayName":"乙肝病毒核心抗体结果","type":"double"},"HBSAB_QUANT_VAL":{"displayName":"乙肝病毒表面抗体结果","type":"double"},"HBSAG_QUANT_REF":{"displayName":"乙肝病毒表面抗原参考值范围","type":"string"},"HBEAB_QUANT_VAL":{"displayName":"乙肝病毒e抗体结果","type":"double"}},"displayName":"HBV免疫学（定量）"},"coagulation_function":{"children":{"APTT_REF":{"displayName":"APTT参考值范围","type":"string"},"INR_VALUE":{"displayName":"国际标准化比值（INR）","type":"double"},"FBG":{"displayName":"纤维蛋白原（g/L）","type":"double"},"APTT_VALUE":{"displayName":"活化部分凝血活酶时间（APTT）（s）","type":"double"},"DDIMER_UNIT":{"displayName":"D-二聚体单位","type":"string"},"INR_REF":{"displayName":"INR参考值范围","type":"string"},"PT_VALUE":{"displayName":"凝血酶原时间（PT）（s）","type":"double"},"DDIMER_REF":{"displayName":"D-二聚体参考值范围","type":"string"},"PT_REF":{"displayName":"PT参考值范围","type":"string"},"TT_VALUE":{"displayName":"凝血酶时间（TT）（s）","type":"double"},"TT_REF":{"displayName":"TT参考值范围","type":"string"},"FBG_REF":{"displayName":"纤维蛋白原参考值范围","type":"string"},"CF_TEST_DATE":{"displayName":"报告日期","format":"yyyy-mm-dd","type":"date"},"DDIMER":{"displayName":"D-二聚体","type":"double"}},"displayName":"凝血功能"},"BR_YN":{"displayName":"有无血常规","type":"string"},"HCV_YN":{"displayName":"有无HCV检验","type":"string"},"HBV_DNA_YN":{"displayName":"有无HBV-DNA检验","type":"string"},"hbv_dna":{"children":{"HBVDNA_VALUE":{"displayName":"DNA","type":"double"},"HBVD_TEST_DATE":{"displayName":"DNA","format":"yyyy-mm-dd","type":"date"},"HBVDNA_REF":{"displayName":"DNA","type":"string"}},"displayName":"HBV"},"hcv":{"children":{"HCV_CAG":{"displayName":"HCV核心抗原","type":"string"},"HCVAB":{"displayName":"HCV抗体结果","type":"string"},"HCVAB_UNIT":{"displayName":"HCV抗体单位","type":"string"},"HCV_TEST_DATE":{"displayName":"报告日期","format":"yyyy-mm-dd","type":"date"},"HCVAB_REF":{"displayName":"HCV抗体参考值范围（定量）","type":"string"}},"displayName":"HCV"},"LKF_YN":{"displayName":"有无肝肾功能检验","type":"string"},"TM_YN":{"displayName":"有无肿瘤标志物检验","type":"string"},"tumor_markers":{"children":{"AFP_REF":{"displayName":"AFP参考值范围","type":"string"},"CEA_REF":{"displayName":"CEA参考值范围","type":"string"},"TM_TEST_DATE":{"displayName":"报告日期","format":"yyyy-mm-dd","type":"date"},"CA19_9_REF":{"displayName":"CA19-9参考值范围","type":"string"},"AFP":{"displayName":"AFP（ug/L）","type":"double"},"CEA":{"displayName":"CEA（ug/L）","type":"double"},"FERR_REF":{"displayName":"铁蛋白参考值范围","type":"string"},"CA19_9":{"displayName":"CA19-9（U/ml）","type":"double"},"FERR":{"displayName":"铁蛋白（ug/L）","type":"double"}},"displayName":"肿瘤标志物"}},"displayName":"检验"},"dx":{"children":{"other_liver_dx_details":{"children":{"OLD_DURATION":{"displayName":"病史时间（年）","type":"double"},"OLD_NAME":{"displayName":"疾病名称","type":"string"},"OLD_DATE":{"displayName":"诊断日期","format":"yyyy-mm-dd","type":"date"}},"displayName":"其他肝脏疾病诊断详情"},"OTHER_LIVER_DX_YN":{"displayName":"有无其他肝脏疾病诊断","type":"string"},"ps_info":{"children":{"PS_NAME":{"displayName":"体力状况评分类型","type":"string"},"PS_DATE":{"displayName":"评分日期","format":"yyyy-mm-dd","type":"date"},"PS_SCORE":{"displayName":"体力状况评分分数","type":"string"}},"displayName":"体力状况评分"},"HCC_DX_YN":{"displayName":"有无肝癌诊断","type":"string"},"hcc_dx_details":{"children":{"HCC_DX_DATE":{"displayName":"诊断日期","format":"yyyy-mm-dd","type":"date"},"HCC_DX_BCLC":{"displayName":"BCLC分期","type":"string"},"HCC_DX_NAME":{"displayName":"诊断名称","type":"string"},"HCC_DX_MET_YN":{"displayName":"有无转移","type":"string"},"HCC_DX_CPC":{"displayName":"Child-Pugh分级","type":"string"},"HCC_DX_RCRNT_YN":{"displayName":"有无复发","type":"string"}},"displayName":"肝癌诊断详情"}},"displayName":"诊断及评估"},"surv_stat":{"children":{"survival_situation":{"children":{"SURVIVAL_STATE":{"displayName":"生存状态","type":"string"}},"displayName":"生存情况"}},"displayName":"生存情况"},"inspect":{"children":{"prev_exm":{"children":{"PLC_DATE":{"displayName":"诊断时间","format":"yyyy-mm-dd","type":"date"},"PLC_CONTENT":{"displayName":"诊断内容","type":"string"},"PLC_EXM":{"displayName":"检查方式","type":"string"}},"displayName":"既往就诊影像及病理检查"},"path_report":{"children":{"other_pr_details":{"children":{"PATH_REPORT_TIME":{"displayName":"报告时间","format":"yyyy-mm-dd","type":"date"},"PATH_DX_ORGN":{"displayName":"病理诊断原文","type":"string"},"PATH_REPORT_CDX":{"displayName":"病理报告临床诊断","type":"string"}},"displayName":"其他病理诊断报告详情"},"lc_path_rprt_details":{"children":{"PATH_REPORT_TIME":{"displayName":"报告时间","format":"yyyy-mm-dd","type":"date"},"CIRRHOSIS_YN":{"displayName":"有无肝硬化","type":"string"},"MVI_GRADE":{"displayName":"MVI风险分级","type":"string"},"TUMOR_THROMBOSIS_YN":{"displayName":"有无脉管瘤栓","type":"string"},"EDGE_STATUS":{"displayName":"切缘情况","type":"string"},"STLT_YN":{"displayName":"有无卫星结节","type":"string"},"MCRVSC_INVSN_YN":{"displayName":"有无微血管侵犯","type":"string"},"DIFF_TEXT":{"displayName":"分化程度（文本）","type":"string"},"ASPR_OR_PNCTR_YN":{"displayName":"是否为针吸/穿刺活检","type":"string"},"HCC_TYPE":{"displayName":"肝癌病理类型","type":"string"},"DIFF_NUM":{"displayName":"分化程度（数字）","type":"string"}},"displayName":"肝癌病理诊断报告详情"},"PATH_REPORT_YN":{"displayName":"有无病理诊断报告","type":"string"}},"displayName":"当次就诊病理诊断报告"},"PAST_LC_DX_YN":{"displayName":"既往检查是否诊断肝癌","type":"string"}},"displayName":"检查"},"xpsr_rf":{"children":{"SMOKE_HX_YN":{"displayName":"有无吸烟史","type":"string"},"ALCOHOL_HX_YN":{"displayName":"有无饮酒史","type":"string"}},"displayName":"暴露及危险因素信息"},"visitinfo":{"children":{"VISIT_DEPT":{"displayName":"就诊科室","type":"string"},"VISIT_START_TIME":{"displayName":"入院（就诊）日期","format":"yyyy-mm-dd","type":"date"},"VISIT_DISCHARGE_TIME":{"displayName":"出院日期","format":"yyyy-mm-dd","type":"date"},"VISIT_TYPE":{"displayName":"就诊类型","type":"string"}},"displayName":"就诊信息"}},"displayName":"就诊"},"patient_info":{"children":{"patient_basicinfo":{"children":{"NATIONALITY":{"displayName":"民族","type":"string"},"CRC_INFO":{"displayName":"录入人","type":"string"},"GENDER":{"displayName":"性别","type":"string"},"PATIENT_SN":{"displayName":"患者编号","type":"string"},"DATE_OF_BIRTH":{"displayName":"出生日期","format":"yyyy","type":"date"}},"displayName":"人口学资料"}},"displayName":"患者基本信息"}}}